contextbase/__init__.py
contextbase/client.py
contextbase_py-1.0.0.dist-info/licenses/LICENSE
contextbase_py-1.0.0.dist-info/METADATA
contextbase_py-1.0.0.dist-info/WHEEL
contextbase_py-1.0.0.dist-info/top_level.txt
contextbase_py-1.0.0.dist-info/RECORD
