Metadata-Version: 2.4
Name: contextbase-py
Version: 1.0.0
Summary: Python SDK for interacting with the ContextBase memory API.
Home-page: https://github.com/imfeniljikadara/contextbase-py
Author: Fenil Jikadara
Classifier: Programming Language :: Python :: 3
Classifier: License :: OSI Approved :: MIT License
Classifier: Operating System :: OS Independent
Requires-Python: >=3.7
License-File: LICENSE
Requires-Dist: requests
Dynamic: author
Dynamic: classifier
Dynamic: description
Dynamic: description-content-type
Dynamic: home-page
Dynamic: license-file
Dynamic: requires-dist
Dynamic: requires-python
Dynamic: summary
